<?xml version="1.0" encoding="utf-8"?>
<Defs>

    <!--=== Cybernetic Spine ===-->
    <!-- ThingDef -->
    <ThingDef ParentName="BodyPartCyberneticBase">
        <defName>BEWH_CyberneticSpine</defName>
        <label>cybernetic spine</label>
        <description>An artificial spine built by a foreign empire a long time ago, the technology used to build these kind of cybernetics is unknown and as such not many exist.</description>
        <descriptionHyperlinks>
            <RecipeDef>BEWH_CyberneticSpine</RecipeDef>
        </descriptionHyperlinks>
        <statBases>
            <MarketValue>2200</MarketValue>
        </statBases>
    </ThingDef>
    <!-- RecipeDef -->
    <RecipeDef ParentName="SurgeryInstallImplantBase">
        <defName>BEWH_CyberneticSpine</defName>
        <label>install cybernetic spine</label>
        <description>Install cybernetic spine.</description>
        <descriptionHyperlinks>
            <ThingDef>BEWH_CyberneticSpine</ThingDef>
            <HediffDef>BEWH_CyberneticSpine</HediffDef>
        </descriptionHyperlinks>
        <jobString>Installing cybernetic spine.</jobString>
        <ingredients>
            <li>
                <filter>
                    <thingDefs>
                        <li>BEWH_CyberneticSpine</li>
                    </thingDefs>
                </filter>
                <count>1</count>
            </li>
        </ingredients>
        <fixedIngredientFilter>
            <thingDefs>
                <li>BEWH_CyberneticSpine</li>
            </thingDefs>
        </fixedIngredientFilter>
        <appliedOnFixedBodyParts>
            <li>Spine</li>
        </appliedOnFixedBodyParts>
        <addsHediff>BEWH_CyberneticSpine</addsHediff>
    </RecipeDef>
    <!-- HediffDef -->
    <HediffDef ParentName="ImplantHediffBase">
        <defName>BEWH_CyberneticSpine</defName>
        <label>cybernetic spine</label>
        <labelNoun>cybernetic spine</labelNoun>
        <description>Installed cybernetic spine.</description>
        <spawnThingOnRemoved>BEWH_CyberneticSpine</spawnThingOnRemoved>
        <addedPartProps>
            <solid>true</solid>
            <partEfficiency>1.4</partEfficiency>
            <betterThanNatural>true</betterThanNatural>
        </addedPartProps>
        <initialSeverity>0</initialSeverity>
        <minSeverity>0</minSeverity>
        <maxSeverity>1</maxSeverity>
        <stages>
            <li>
                <label>Inactive</label>
                <minSeverity>0</minSeverity>
            </li>
            <li>
                <label>Active</label>
                <minSeverity>1</minSeverity>
                <statOffsets>
                    <CarryingCapacity>60</CarryingCapacity>
                </statOffsets>
            </li>
        </stages>
        <comps>
            <li Class="Cybernetics40k.HediffCompProperties_PassiveInternalPowerUser">
                <powerUsage>4</powerUsage>
            </li>
        </comps>
    </HediffDef>

</Defs>