<?xml version="1.0" encoding="utf-8"?>
<Defs>

    <!--=== Utility Mechadendrite ===-->
    <!-- ThingDef -->
    <ThingDef ParentName="BodyPartCyberneticBase">
        <defName>BEWH_UtilityMechadendrite</defName>
        <label>utility mechadendrite</label>
        <description>This mechadendrite incorporates a selection of useful tools and attachments. \n\nRequires the pawn to have an installed Mechadendrite Neural System to be able to install this.</description>
        <descriptionHyperlinks>
            <RecipeDef>BEWH_UtilityMechadendrite</RecipeDef>
        </descriptionHyperlinks>
        <statBases>
            <MarketValue>2500</MarketValue>
        </statBases>
    </ThingDef>
    <!-- RecipeDef -->
    <RecipeDef ParentName="SurgeryInstallImplantBase">
        <defName>BEWH_UtilityMechadendrite</defName>
        <workerClass>Core40k.Recipe_InstallImplantRequiringHediff</workerClass>
        <label>install utility mechadendrite</label>
        <description>Install utility mechadendrite.</description>
        <descriptionHyperlinks>
            <ThingDef>BEWH_UtilityMechadendrite</ThingDef>
            <HediffDef>BEWH_UtilityMechadendrite</HediffDef>
        </descriptionHyperlinks>
        <jobString>Installing utility mechadendrite.</jobString>
        <ingredients>
            <li>
                <filter>
                    <thingDefs>
                        <li>BEWH_UtilityMechadendrite</li>
                    </thingDefs>
                </filter>
                <count>1</count>
            </li>
        </ingredients>
        <fixedIngredientFilter>
            <thingDefs>
                <li>BEWH_UtilityMechadendrite</li>
            </thingDefs>
        </fixedIngredientFilter>
        <appliedOnFixedBodyParts>
            <li>Shoulder</li>
        </appliedOnFixedBodyParts>
        <addsHediff>BEWH_UtilityMechadendrite</addsHediff>
        <modExtensions>
            <li Class="Core40k.DefModExtension_RequiresHediff">
                <hediffDef>BEWH_MechadendriteNeuralSystem</hediffDef>
            </li>
        </modExtensions>
    </RecipeDef>
    <!-- HediffDef -->
    <HediffDef ParentName="ImplantHediffBase">
        <defName>BEWH_UtilityMechadendrite</defName>
        <label>utility mechadendrite</label>
        <labelNoun>utility mechadendrite</labelNoun>
        <description>Installed utility mechadendrite.</description>
        <initialSeverity>0</initialSeverity>
        <minSeverity>0</minSeverity>
        <maxSeverity>1</maxSeverity>
        <stages>
            <li>
                <label>Inactive</label>
                <minSeverity>0</minSeverity>
                <statOffsets>
                    <CarryingCapacity>15</CarryingCapacity>
                    <ConstructionSpeed>0.075</ConstructionSpeed>
                    <GeneralLaborSpeed>0.075</GeneralLaborSpeed>
                    <SmeltingSpeed>0.075</SmeltingSpeed>
                </statOffsets>
                <capMods>
                    <li>
                        <capacity>Moving</capacity>
                        <postFactor>0.95</postFactor>
                    </li>
                </capMods>
            </li>
            <li>
                <label>Active</label>
                <minSeverity>1</minSeverity>
                <statOffsets>
                    <CarryingCapacity>60</CarryingCapacity>
                    <ConstructionSpeed>0.3</ConstructionSpeed>
                    <GeneralLaborSpeed>0.3</GeneralLaborSpeed>
                    <SmeltingSpeed>0.3</SmeltingSpeed>
                </statOffsets>
            </li>
        </stages>
        <comps>
            <li Class="HediffCompProperties_VerbGiver">
                <tools>
                    <li>
                        <label>utility mechadendrite</label>
                        <capacities>
                            <li>Poke</li>
                        </capacities>
                        <power>15</power>
                        <cooldownTime>2.5</cooldownTime>
                    </li>
                </tools>
            </li>
            <li Class="HediffCompProperties_GiveAbility">
                <abilityDefs>
                    <li>BEWH_UtilityMechadendriteFirefoam</li>
                    <li>BEWH_UtilityMechadendriteSmoke</li>
                </abilityDefs>
            </li>
            <li Class="Cybernetics40k.HediffCompProperties_PassiveInternalPowerUser">
                <powerUsage>2</powerUsage>
            </li>
        </comps>
    </HediffDef>
    <!-- AbilityDef Foam -->
    <AbilityDef>
        <defName>BEWH_UtilityMechadendriteFirefoam</defName>
        <label>firefoam</label>
        <description>Release a fire-retardant foam in a circular area.</description>
        <iconPath>UI/Abilities/UtilityFirefoam</iconPath>
        <cooldownTicksRange>240000</cooldownTicksRange>
        <displayGizmoWhileUndrafted>false</displayGizmoWhileUndrafted>
        <disableGizmoWhileUndrafted>true</disableGizmoWhileUndrafted>
        <targetRequired>false</targetRequired>
        <hostile>false</hostile>
        <category>BEWH_Cybernetics</category>
        <verbProperties>
            <verbClass>Verb_CastAbility</verbClass>
            <warmupTime>0.25</warmupTime>
            <requireLineOfSight>false</requireLineOfSight>
            <drawAimPie>false</drawAimPie>
            <range>4.9</range>
            <targetParams>
                <canTargetSelf>true</canTargetSelf>
            </targetParams>
        </verbProperties>
        <comps>
            <li Class="CompProperties_AbilityFirefoampop">
                <firefoamRadius>5</firefoamRadius>
                <clamorType>Ability</clamorType>
                <clamorRadius>15</clamorRadius>
            </li>
        </comps>
    </AbilityDef>
    <!-- AbilityDef Smoke -->
    <AbilityDef>
        <defName>BEWH_UtilityMechadendriteSmoke</defName>
        <label>smoke</label>
        <description>Release compressed smoke from concealed vents. Smoke reduces the accuracy of any shot fired through it, and prevents turrets from locking on entirely.</description>
        <iconPath>UI/Abilities/UtilitySmoke</iconPath>
        <cooldownTicksRange>360000</cooldownTicksRange>
        <targetRequired>false</targetRequired>
        <hostile>false</hostile>
        <category>BEWH_Cybernetics</category>
        <verbProperties>
            <verbClass>Verb_CastAbility</verbClass>
            <warmupTime>1</warmupTime>
            <range>4.9</range>
            <drawAimPie>false</drawAimPie>
            <targetParams>
                <canTargetSelf>true</canTargetSelf>
            </targetParams>
        </verbProperties>
        <comps>
            <li Class="CompProperties_AbilitySmokepop">
                <smokeRadius>5</smokeRadius>
                <clamorType>Ability</clamorType>
                <clamorRadius>15</clamorRadius>
            </li>
        </comps>
    </AbilityDef>

</Defs>